espnet/__init__.py
espnet/version.txt
espnet/asr/__init__.py
espnet/asr/asr_mix_utils.py
espnet/asr/asr_utils.py
espnet/asr/chainer_backend/__init__.py
espnet/asr/chainer_backend/asr.py
espnet/asr/pytorch_backend/__init__.py
espnet/asr/pytorch_backend/asr.py
espnet/asr/pytorch_backend/asr_init.py
espnet/asr/pytorch_backend/asr_mix.py
espnet/asr/pytorch_backend/recog.py
espnet/bin/__init__.py
espnet/bin/asr_align.py
espnet/bin/asr_enhance.py
espnet/bin/asr_recog.py
espnet/bin/asr_train.py
espnet/bin/lm_train.py
espnet/bin/mt_train.py
espnet/bin/mt_trans.py
espnet/bin/st_train.py
espnet/bin/st_trans.py
espnet/bin/tts_decode.py
espnet/bin/tts_train.py
espnet/bin/vc_decode.py
espnet/bin/vc_train.py
espnet/distributed/__init__.py
espnet/lm/__init__.py
espnet/lm/lm_utils.py
espnet/lm/chainer_backend/__init__.py
espnet/lm/chainer_backend/extlm.py
espnet/lm/chainer_backend/lm.py
espnet/lm/pytorch_backend/__init__.py
espnet/lm/pytorch_backend/extlm.py
espnet/lm/pytorch_backend/lm.py
espnet/mt/__init__.py
espnet/mt/mt_utils.py
espnet/mt/pytorch_backend/__init__.py
espnet/mt/pytorch_backend/mt.py
espnet/nets/__init__.py
espnet/nets/asr_interface.py
espnet/nets/batch_beam_search.py
espnet/nets/batch_beam_search_online.py
espnet/nets/batch_beam_search_online_sim.py
espnet/nets/beam_search.py
espnet/nets/beam_search_partially_AR.py
espnet/nets/beam_search_timesync.py
espnet/nets/beam_search_timesync_streaming.py
espnet/nets/beam_search_transducer.py
espnet/nets/ctc_prefix_score.py
espnet/nets/e2e_asr_common.py
espnet/nets/e2e_mt_common.py
espnet/nets/lm_interface.py
espnet/nets/mt_interface.py
espnet/nets/scorer_interface.py
espnet/nets/st_interface.py
espnet/nets/transducer_decoder_interface.py
espnet/nets/tts_interface.py
espnet/nets/chainer_backend/__init__.py
espnet/nets/chainer_backend/asr_interface.py
espnet/nets/chainer_backend/ctc.py
espnet/nets/chainer_backend/deterministic_embed_id.py
espnet/nets/chainer_backend/e2e_asr.py
espnet-202509.dist-info/LICENSE
espnet-202509.dist-info/METADATA
espnet-202509.dist-info/WHEEL
espnet-202509.dist-info/top_level.txt
espnet-202509.dist-info/RECORD
