Metadata-Version: 2.1
Name: espnet
Version: 202509
Summary: ESPnet: end-to-end speech processing toolkit
Home-page: http://github.com/espnet/espnet
Author: Shinji Watanabe
Author-email: shinjiw@ieee.org
License: Apache Software License
Classifier: Programming Language :: Python
Classifier: Programming Language :: Python :: 3
Classifier: Programming Language :: Python :: 3.9
Classifier: Programming Language :: Python :: 3.10
Classifier: Programming Language :: Python :: 3.11
Classifier: Programming Language :: Python :: 3.12
Classifier: Programming Language :: Python :: 3.13
Classifier: Development Status :: 5 - Production/Stable
Classifier: Intended Audience :: Science/Research
Classifier: Operating System :: POSIX :: Linux
Classifier: License :: OSI Approved :: Apache Software License
Classifier: Topic :: Software Development :: Libraries :: Python Modules
Requires-Python: >=3.9.0
License-File: LICENSE
Requires-Dist: setuptools<74.0.0,>=38.5.1
Requires-Dist: packaging
Requires-Dist: configargparse>=1.2.1
Requires-Dist: typeguard
Requires-Dist: humanfriendly
Requires-Dist: scipy>=1.4.1
Requires-Dist: filelock
Requires-Dist: librosa>=0.10.2
Requires-Dist: jamo==0.4.1
Requires-Dist: PyYAML>=5.1.2
Requires-Dist: soundfile>=0.10.2
Requires-Dist: h5py>=2.10.0
Requires-Dist: kaldiio>=2.18.0
Requires-Dist: torch>=1.11.0
Requires-Dist: torch-complex
Requires-Dist: nltk>=3.4.5
Requires-Dist: numpy>=2.0.0
Requires-Dist: protobuf
Requires-Dist: hydra-core
Requires-Dist: opt-einsum
Requires-Dist: lightning
Requires-Dist: sentencepiece==0.2.0
Requires-Dist: pyworld>=0.3.4
Requires-Dist: pypinyin<=0.44.0
Requires-Dist: espnet-tts-frontend
Requires-Dist: ci-sdr
Requires-Dist: fast-bss-eval==0.1.3
Requires-Dist: asteroid-filterbanks==0.4.0
Requires-Dist: editdistance
Requires-Dist: importlib-metadata<5.0
Provides-Extra: all
Requires-Dist: torchaudio; extra == "all"
Requires-Dist: torch-optimizer; extra == "all"
Requires-Dist: fairscale; extra == "all"
Requires-Dist: transformers; extra == "all"
Requires-Dist: evaluate; extra == "all"
Requires-Dist: matplotlib; extra == "all"
Requires-Dist: pillow==9.5.0; extra == "all"
Requires-Dist: wandb; extra == "all"
Requires-Dist: tensorboard>=1.14; extra == "all"
Requires-Dist: espnet-model-zoo; extra == "all"
Requires-Dist: gdown; extra == "all"
Requires-Dist: resampy; extra == "all"
Requires-Dist: pysptk>=0.2.1; extra == "all"
Requires-Dist: morfessor; extra == "all"
Requires-Dist: youtube-dl; extra == "all"
Requires-Dist: nnmnkwii; extra == "all"
Requires-Dist: museval>=0.2.1; extra == "all"
Requires-Dist: pystoi>=0.2.2; extra == "all"
Requires-Dist: mir-eval>=0.6; extra == "all"
Requires-Dist: fastdtw; extra == "all"
Requires-Dist: nara-wpe>=0.0.5; extra == "all"
Requires-Dist: sacrebleu>=1.5.1; extra == "all"
Requires-Dist: praatio<7,>=6; extra == "all"
Requires-Dist: scikit-learn>=1.0.0; extra == "all"
Provides-Extra: doc
Requires-Dist: Jinja2<=3.1; extra == "doc"
Requires-Dist: sphinx<9.0.0; extra == "doc"
Requires-Dist: sphinx-rtd-theme>=0.2.4; extra == "doc"
Requires-Dist: sphinx-argparse>=0.2.5; extra == "doc"
Requires-Dist: commonmark==0.8.1; extra == "doc"
Requires-Dist: myst-parser; extra == "doc"
Requires-Dist: nbsphinx>=0.4.2; extra == "doc"
Requires-Dist: sphinx-markdown-tables>=0.0.12; extra == "doc"
Requires-Dist: jupyterlab<5; extra == "doc"
Requires-Dist: sphinx-markdown-builder; extra == "doc"
Provides-Extra: recipe
Requires-Dist: espnet-model-zoo; extra == "recipe"
Requires-Dist: gdown; extra == "recipe"
Requires-Dist: resampy; extra == "recipe"
Requires-Dist: pysptk>=0.2.1; extra == "recipe"
Requires-Dist: morfessor; extra == "recipe"
Requires-Dist: youtube-dl; extra == "recipe"
Requires-Dist: nnmnkwii; extra == "recipe"
Requires-Dist: museval>=0.2.1; extra == "recipe"
Requires-Dist: pystoi>=0.2.2; extra == "recipe"
Requires-Dist: mir-eval>=0.6; extra == "recipe"
Requires-Dist: fastdtw; extra == "recipe"
Requires-Dist: nara-wpe>=0.0.5; extra == "recipe"
Requires-Dist: sacrebleu>=1.5.1; extra == "recipe"
Requires-Dist: praatio<7,>=6; extra == "recipe"
Requires-Dist: scikit-learn>=1.0.0; extra == "recipe"
Provides-Extra: test
Requires-Dist: pytest<8.4.0,>=7.0.0; extra == "test"
Requires-Dist: pytest-timeouts>=1.2.1; extra == "test"
Requires-Dist: pytest-pythonpath>=0.7.3; extra == "test"
Requires-Dist: pytest-cov>=2.7.1; extra == "test"
Requires-Dist: hacking>=2.0.0; extra == "test"
Requires-Dist: mock>=2.0.0; extra == "test"
Requires-Dist: pycodestyle; extra == "test"
Requires-Dist: jsondiff>=2.0.0; extra == "test"
Requires-Dist: flake8>=3.7.8; extra == "test"
Requires-Dist: flake8-docstrings>=1.3.1; extra == "test"
Requires-Dist: black; extra == "test"
Requires-Dist: isort; extra == "test"
Requires-Dist: matplotlib; extra == "test"
Requires-Dist: pillow==9.5.0; extra == "test"
Requires-Dist: wandb; extra == "test"
Requires-Dist: tensorboard>=1.14; extra == "test"
Provides-Extra: train
Requires-Dist: matplotlib; extra == "train"
Requires-Dist: pillow==9.5.0; extra == "train"
Requires-Dist: wandb; extra == "train"
Requires-Dist: tensorboard>=1.14; extra == "train"
